[
  {
    "date": "2026-06-18",
    "time": "",
    "group": "A",
    "home": "Czechia",
    "away": "South Africa",
    "venue": "Atlanta",
    "status": "kommande",
    "score": null,
    "source": "ESPN"
  },
  {
    "date": "2026-06-18",
    "time": "21:00",
    "group": "B",
    "home": "Switzerland",
    "away": "Bosnia and Herzegovina",
    "venue": "Inglewood, Calif.",
    "status": "kommande",
    "score": null,
    "source": "ESPN"
  },
  {
    "date": "2026-06-19",
    "time": "00:00",
    "group": "B",
    "home": "Canada",
    "away": "Qatar",
    "venue": "Vancouver, Canada",
    "status": "kommande",
    "score": null,
    "source": "ESPN"
  },
  {
    "date": "2026-06-19",
    "time": "05:00",
    "group": "A",
    "home": "Mexico",
    "away": "South Korea",
    "venue": "Zapopan, Mexico",
    "status": "kommande",
    "score": null,
    "source": "ESPN"
  },
  {
    "date": "2026-06-19",
    "time": "21:00",
    "group": "D",
    "home": "United States",
    "away": "Australia",
    "venue": "Seattle",
    "status": "kommande",
    "score": null,
    "source": "ESPN"
  },
  {
    "date": "2026-06-20",
    "time": "00:00",
    "group": "C",
    "home": "Scotland",
    "away": "Morocco",
    "venue": "Foxborough, Mass.",
    "status": "kommande",
    "score": null,
    "source": "ESPN"
  },
  {
    "date": "2026-06-20",
    "time": "03:00",
    "group": "C",
    "home": "Brazil",
    "away": "Haiti",
    "venue": "Philadelphia",
    "status": "kommande",
    "score": null,
    "source": "ESPN"
  },
  {
    "date": "2026-06-20",
    "time": "06:00",
    "group": "D",
    "home": "Türkiye",
    "away": "Paraguay",
    "venue": "Santa Clara, Calif.",
    "status": "kommande",
    "score": null,
    "source": "ESPN"
  },
  {
    "date": "2026-06-20",
    "time": "19:00",
    "group": "F",
    "home": "Netherlands",
    "away": "Sweden",
    "venue": "Houston",
    "status": "kommande",
    "score": null,
    "source": "ESPN"
  },
  {
    "date": "2026-06-20",
    "time": "22:00",
    "group": "E",
    "home": "Germany",
    "away": "Ivory Coast",
    "venue": "Toronto",
    "status": "kommande",
    "score": null,
    "source": "ESPN"
  },
  {
    "date": "2026-06-21",
    "time": "02:00",
    "group": "E",
    "home": "Ecuador",
    "away": "Curaçao",
    "venue": "Kansas City, Mo.",
    "status": "kommande",
    "score": null,
    "source": "ESPN"
  },
  {
    "date": "2026-06-21",
    "time": "06:00",
    "group": "F",
    "home": "Tunisia",
    "away": "Japan",
    "venue": "Guadalupe, Mexico",
    "status": "kommande",
    "score": null,
    "source": "ESPN"
  },
  {
    "date": "2026-06-21",
    "time": "",
    "group": "H",
    "home": "Spain",
    "away": "Saudi Arabia",
    "venue": "Atlanta",
    "status": "kommande",
    "score": null,
    "source": "ESPN"
  },
  {
    "date": "2026-06-21",
    "time": "21:00",
    "group": "G",
    "home": "Belgium",
    "away": "Iran",
    "venue": "Inglewood, Calif.",
    "status": "kommande",
    "score": null,
    "source": "ESPN"
  },
  {
    "date": "2026-06-22",
    "time": "00:00",
    "group": "H",
    "home": "Uruguay",
    "away": "Cape Verde",
    "venue": "Miami Gardens, Fla.",
    "status": "kommande",
    "score": null,
    "source": "ESPN"
  },
  {
    "date": "2026-06-22",
    "time": "03:00",
    "group": "G",
    "home": "New Zealand",
    "away": "Egypt",
    "venue": "Vancouver",
    "status": "kommande",
    "score": null,
    "source": "ESPN"
  },
  {
    "date": "2026-06-22",
    "time": "19:00",
    "group": "J",
    "home": "Argentina",
    "away": "Austria",
    "venue": "Arlington, Texas",
    "status": "kommande",
    "score": null,
    "source": "ESPN"
  },
  {
    "date": "2026-06-22",
    "time": "23:00",
    "group": "I",
    "home": "France",
    "away": "Iraq",
    "venue": "Philadelphia",
    "status": "kommande",
    "score": null,
    "source": "ESPN"
  },
  {
    "date": "2026-06-23",
    "time": "02:00",
    "group": "I",
    "home": "Norway",
    "away": "Senegal",
    "venue": "East Rutherford, N.J.",
    "status": "kommande",
    "score": null,
    "source": "ESPN"
  },
  {
    "date": "2026-06-23",
    "time": "05:00",
    "group": "J",
    "home": "Jordan",
    "away": "Algeria",
    "venue": "Santa Clara, Calif.",
    "status": "kommande",
    "score": null,
    "source": "ESPN"
  },
  {
    "date": "2026-06-23",
    "time": "19:00",
    "group": "K",
    "home": "Portugal",
    "away": "Uzbekistan",
    "venue": "Houston",
    "status": "kommande",
    "score": null,
    "source": "ESPN"
  },
  {
    "date": "2026-06-23",
    "time": "22:00",
    "group": "L",
    "home": "England",
    "away": "Ghana",
    "venue": "Foxborough, Mass.",
    "status": "kommande",
    "score": null,
    "source": "ESPN"
  },
  {
    "date": "2026-06-24",
    "time": "01:00",
    "group": "L",
    "home": "Panama",
    "away": "Croatia",
    "venue": "Toronto",
    "status": "kommande",
    "score": null,
    "source": "ESPN"
  },
  {
    "date": "2026-06-24",
    "time": "04:00",
    "group": "K",
    "home": "Colombia",
    "away": "DR Congo",
    "venue": "Zapopan, Mexico",
    "status": "kommande",
    "score": null,
    "source": "ESPN"
  },
  {
    "date": "2026-06-24",
    "time": "21:00",
    "group": "B",
    "home": "Switzerland",
    "away": "Canada",
    "venue": "Vancouver, Canada",
    "status": "kommande",
    "score": null,
    "source": "ESPN"
  },
  {
    "date": "2026-06-24",
    "time": "21:00",
    "group": "B",
    "home": "Bosnia and Herzegovina",
    "away": "Qatar",
    "venue": "Seattle",
    "status": "kommande",
    "score": null,
    "source": "ESPN"
  },
  {
    "date": "2026-06-25",
    "time": "00:00",
    "group": "C",
    "home": "Scotland",
    "away": "Brazil",
    "venue": "Miami Gardens, Fla.",
    "status": "kommande",
    "score": null,
    "source": "ESPN"
  },
  {
    "date": "2026-06-25",
    "time": "00:00",
    "group": "C",
    "home": "Morocco",
    "away": "Haiti",
    "venue": "Atlanta",
    "status": "kommande",
    "score": null,
    "source": "ESPN"
  },
  {
    "date": "2026-06-25",
    "time": "03:00",
    "group": "A",
    "home": "Czechia",
    "away": "Mexico",
    "venue": "Mexico City",
    "status": "kommande",
    "score": null,
    "source": "ESPN"
  },
  {
    "date": "2026-06-25",
    "time": "03:00",
    "group": "A",
    "home": "South Africa",
    "away": "South Korea",
    "venue": "Guadalupe, Mexico",
    "status": "kommande",
    "score": null,
    "source": "ESPN"
  },
  {
    "date": "2026-06-25",
    "time": "22:00",
    "group": "E",
    "home": "Ecuador",
    "away": "Germany",
    "venue": "East Rutherford, N.J.",
    "status": "kommande",
    "score": null,
    "source": "ESPN"
  },
  {
    "date": "2026-06-25",
    "time": "22:00",
    "group": "E",
    "home": "Curacao",
    "away": "Ivory Coast",
    "venue": "Philadelphia",
    "status": "kommande",
    "score": null,
    "source": "ESPN"
  },
  {
    "date": "2026-06-26",
    "time": "01:00",
    "group": "F",
    "home": "Japan",
    "away": "Sweden",
    "venue": "Arlington, Texas",
    "status": "kommande",
    "score": null,
    "source": "ESPN"
  },
  {
    "date": "2026-06-26",
    "time": "01:00",
    "group": "F",
    "home": "Tunisia",
    "away": "Netherlands",
    "venue": "Kansas City, Mo.",
    "status": "kommande",
    "score": null,
    "source": "ESPN"
  },
  {
    "date": "2026-06-26",
    "time": "04:00",
    "group": "D",
    "home": "Türkiye",
    "away": "United States",
    "venue": "Inglewood, Calif.",
    "status": "kommande",
    "score": null,
    "source": "ESPN"
  },
  {
    "date": "2026-06-26",
    "time": "04:00",
    "group": "D",
    "home": "Paraguay",
    "away": "Australia",
    "venue": "Santa Clara, Calif.",
    "status": "kommande",
    "score": null,
    "source": "ESPN"
  },
  {
    "date": "2026-06-26",
    "time": "21:00",
    "group": "I",
    "home": "Norway",
    "away": "France",
    "venue": "Foxborough, Mass.",
    "status": "kommande",
    "score": null,
    "source": "ESPN"
  },
  {
    "date": "2026-06-26",
    "time": "21:00",
    "group": "I",
    "home": "Senegal",
    "away": "Iraq",
    "venue": "Toronto",
    "status": "kommande",
    "score": null,
    "source": "ESPN"
  },
  {
    "date": "2026-06-27",
    "time": "02:00",
    "group": "H",
    "home": "Cape Verde",
    "away": "Saudi Arabia",
    "venue": "Houston",
    "status": "kommande",
    "score": null,
    "source": "ESPN"
  },
  {
    "date": "2026-06-27",
    "time": "02:00",
    "group": "H",
    "home": "Uruguay",
    "away": "Spain",
    "venue": "Zapopan, Mexico",
    "status": "kommande",
    "score": null,
    "source": "ESPN"
  },
  {
    "date": "2026-06-27",
    "time": "05:00",
    "group": "G",
    "home": "Egypt",
    "away": "Iran",
    "venue": "Seattle",
    "status": "kommande",
    "score": null,
    "source": "ESPN"
  },
  {
    "date": "2026-06-27",
    "time": "05:00",
    "group": "G",
    "home": "New Zealand",
    "away": "Belgium",
    "venue": "Vancouver, Canada",
    "status": "kommande",
    "score": null,
    "source": "ESPN"
  },
  {
    "date": "2026-06-27",
    "time": "23:00",
    "group": "L",
    "home": "Panama",
    "away": "England",
    "venue": "East Rutherford, N.J.",
    "status": "kommande",
    "score": null,
    "source": "ESPN"
  },
  {
    "date": "2026-06-27",
    "time": "23:00",
    "group": "L",
    "home": "Croatia",
    "away": "Ghana",
    "venue": "Philadelphia",
    "status": "kommande",
    "score": null,
    "source": "ESPN"
  },
  {
    "date": "2026-06-28",
    "time": "01:30",
    "group": "K",
    "home": "Colombia",
    "away": "Portugal",
    "venue": "Miami Gardens, Fla.",
    "status": "kommande",
    "score": null,
    "source": "ESPN"
  },
  {
    "date": "2026-06-28",
    "time": "01:30",
    "group": "K",
    "home": "DR Congo",
    "away": "Uzbekistan",
    "venue": "Atlanta Stadium",
    "status": "kommande",
    "score": null,
    "source": "ESPN"
  },
  {
    "date": "2026-06-28",
    "time": "04:00",
    "group": "J",
    "home": "Algeria",
    "away": "Austria",
    "venue": "Kansas City, Mo.",
    "status": "kommande",
    "score": null,
    "source": "ESPN"
  },
  {
    "date": "2026-06-28",
    "time": "04:00",
    "group": "J",
    "home": "Jordan",
    "away": "Argentina",
    "venue": "Arlington, Texas",
    "status": "kommande",
    "score": null,
    "source": "ESPN"
  }
]